WebDispatch-1.3.dist-info/metadata.json
WebDispatch-1.3.dist-info/METADATA
WebDispatch-1.3.dist-info/top_level.txt
WebDispatch-1.3.dist-info/RECORD
WebDispatch-1.3.dist-info/WHEEL
WebDispatch-1.3.dist-info/entry_points.txt
WebDispatch-1.3.dist-info/DESCRIPTION.rst
webdispatch/paster.py
webdispatch/urldispatcher.py
webdispatch/testing.py
webdispatch/uritemplate.py
webdispatch/methoddispatcher.py
webdispatch/mixins.py
webdispatch/dummyapps.py
webdispatch/base.py
webdispatch/__init__.py
webdispatch/tests/test_urldispatcher.py
webdispatch/tests/test_uritemplate.py
webdispatch/tests/test_paster.py
webdispatch/tests/test_base.py
webdispatch/tests/test_methoddispatcher.py
webdispatch/tests/test_mixins.py
webdispatch/tests/__init__.py
